Eupompos-0.1.1.dist-info/DESCRIPTION.rst
Eupompos-0.1.1.dist-info/METADATA
Eupompos-0.1.1.dist-info/RECORD
Eupompos-0.1.1.dist-info/WHEEL
Eupompos-0.1.1.dist-info/entry_points.txt
Eupompos-0.1.1.dist-info/metadata.json
Eupompos-0.1.1.dist-info/top_level.txt
eupompos/__init__.py
eupompos/cmdlineparser.py
eupompos/configfile.py
eupompos/cppfuncdecl.py
eupompos/cppparser.py
eupompos/cppparserstate.py
eupompos/filetools.py
eupompos/liaf.py
eupompos/main.py
eupompos/messages.py
eupompos/parser.py
eupompos/parserreport.py
eupompos/pyfuncdecl.py
eupompos/pyparser.py
eupompos/pyparserstate.py
eupompos/settings.py
eupompos/strtools.py
eupompos/tests/__init__.py
eupompos/tests/cppparser.py
eupompos/tests/tests_cppparser.py
eupompos/tests/tests_liaf.py
eupompos/tests/tests_pyfunctiondecl.py
eupompos/tests/tests_pyparser.py
eupompos/tests/tests_strtools.py
