Metadata-Version: 2.0
Name: Eupompos
Version: 0.1.1
Summary: GPLv3/Python3/CLI very naive [Python|C++]Qt parser to get informations about Qt signals
Home-page: https://github.com/suizokukan/eupompos
Author: Xavier Faure (suizokukan)
Author-email: suizokukan @T orange D@T fr
License: GPL-3.0
Keywords: c++ cpp python qt
Platform: UNKNOWN
Classifier: Development Status :: 3 - Alpha
Classifier: Intended Audience :: Developers
Classifier: Topic :: Utilities
Classifier: License :: OSI Approved :: GNU General Public License v3 (GPLv3)
Classifier: Programming Language :: Python :: 3
